kavanaghdistributions/__init__.py
kavanaghdistributions/classes.py
kavanaghdistributions/functions.py
kavanaghdistributions-1.dist-info/LICENSE
kavanaghdistributions-1.dist-info/METADATA
kavanaghdistributions-1.dist-info/WHEEL
kavanaghdistributions-1.dist-info/top_level.txt
kavanaghdistributions-1.dist-info/RECORD
