Metadata-Version: 2.1
Name: kavanaghdistributions
Version: 1
Summary: Various Functions and Methods for sample distributions
Home-page: https://github.com/BAK2K3/kavanaghdistributions
Author: Benjamin Kavanagh
Author-email: benjamin.a.kavanagh@gmail.com
License: MIT
Platform: UNKNOWN
Classifier: Programming Language :: Python :: 3
Classifier: License :: OSI Approved :: MIT License
Classifier: Operating System :: OS Independent
Requires-Python: >=3.7
Requires-Dist: numpy
